bpaingest/__init__.py
bpaingest/abstract.py
bpaingest/cli.py
bpaingest/dump.py
bpaingest/genhash.py
bpaingest/handlers/__init__.py
bpaingest/handlers/base_contextual_metadata_apply.py
bpaingest/handlers/base_contextual_metadata_sheet.py
bpaingest/handlers/bpam_csv_export.py
bpaingest/handlers/ckan_check_all_resources_integrities.py
bpaingest/handlers/ckan_resource_integrity_check.py
bpaingest/handlers/ckan_service.py
bpaingest/handlers/common.py
bpaingest/handlers/sheets_to_csv.py
bpaingest/libs/__init__.py
bpaingest/libs/bpa_constants.py
bpaingest/libs/common_resources.py
bpaingest/libs/excel_wrapper.py
bpaingest/libs/fetch_data.py
bpaingest/libs/ingest_utils.py
bpaingest/libs/md5lines.py
bpaingest/libs/multihash.py
bpaingest/libs/test_libs.py
bpaingest/metadata.py
bpaingest/ncbi.py
bpaingest/ops.py
bpaingest/organizations.py
bpaingest/pkgcache.py
bpaingest/projects/__init__.py
bpaingest/projects/amdb/__init__.py
bpaingest/projects/amdb/contextual.py
bpaingest/projects/amdb/files.py
bpaingest/projects/amdb/ingest.py
bpaingest/projects/amdb/test_amdb.py
bpaingest/projects/amdb/tracking.py
bpaingest/projects/amdb/vocabularies.py
bpaingest/projects/barcode/__init__.py
bpaingest/projects/barcode/ingest.py
bpaingest/projects/gap/__init__.py
bpaingest/projects/gap/contextual.py
bpaingest/projects/gap/files.py
bpaingest/projects/gap/ingest.py
bpaingest/projects/gap/test_gap.py
bpaingest/projects/gap/tracking.py
bpaingest/projects/gbr/__init__.py
bpaingest/projects/gbr/files.py
bpaingest/projects/gbr/ingest.py
bpaingest/projects/melanoma/__init__.py
bpaingest/projects/melanoma/ingest.py
bpaingest/projects/omg/__init__.py
bpaingest/projects/omg/contextual.py
bpaingest/projects/omg/files.py
bpaingest/projects/omg/ingest.py
bpaingest/projects/omg/test_omg.py
bpaingest/projects/omg/tracking.py
bpaingest/projects/sepsis/__init__.py
bpaingest/projects/sepsis/contextual.py
bpaingest/projects/sepsis/files.py
bpaingest/projects/sepsis/ingest.py
bpaingest/projects/sepsis/strains.py
bpaingest-6.4.2.dist-info/entry_points.txt
bpaingest-6.4.2.dist-info/LICENSE
bpaingest-6.4.2.dist-info/WHEEL
bpaingest-6.4.2.dist-info/METADATA
bpaingest-6.4.2.dist-info/RECORD
