Metadata-Version: 2.1
Name: bpaingest
Version: 6.4.2
Summary: Data management for Bioplatforms Australia projects
Author: Grahame Bowland
Author-email: grahame.bowland@qcif.edu.au
Requires-Python: >=3.6
Classifier: Programming Language :: Python :: 3
Classifier: Programming Language :: Python :: 3.6
Classifier: Programming Language :: Python :: 3.7
Classifier: Programming Language :: Python :: 3.8
Requires-Dist: beautifulsoup4 (>=4.9.0,<5.0.0)
Requires-Dist: boto3 (>=1.12.45,<2.0.0)
Requires-Dist: bpasslh (>=2.1.0,<3.0.0)
Requires-Dist: ckanapi (>=4.3,<5.0)
Requires-Dist: google-api-python-client (>=1.8.2,<2.0.0)
Requires-Dist: python-dateutil (>=2.8.1,<3.0.0)
Requires-Dist: requests (>=2.23.0,<3.0.0)
Requires-Dist: unipath (>=1.1,<2.0)
Requires-Dist: xlrd (>=1.2.0,<2.0.0)
Requires-Dist: xlwt (>=1.3.0,<2.0.0)
